causal_inference_engine/__init__.py
causal_inference_engine/_nbdev.py
causal_inference_engine/core.py
causal_inference_engine-0.0.2.dist-info/LICENSE
causal_inference_engine-0.0.2.dist-info/METADATA
causal_inference_engine-0.0.2.dist-info/WHEEL
causal_inference_engine-0.0.2.dist-info/entry_points.txt
causal_inference_engine-0.0.2.dist-info/top_level.txt
causal_inference_engine-0.0.2.dist-info/RECORD
